mcp_server_okppt/__init__.py
mcp_server_okppt/__main__.py
mcp_server_okppt/cli.py
mcp_server_okppt/ppt_operations.py
mcp_server_okppt/server.py
mcp_server_okppt/svg_module.py
mcp_server_okppt-0.2.0.dist-info/licenses/LICENSE
mcp_server_okppt-0.2.0.dist-info/METADATA
mcp_server_okppt-0.2.0.dist-info/WHEEL
mcp_server_okppt-0.2.0.dist-info/entry_points.txt
mcp_server_okppt-0.2.0.dist-info/top_level.txt
mcp_server_okppt-0.2.0.dist-info/RECORD
