Metadata-Version: 2.4
Name: mcp-server-okppt
Version: 0.2.0
Summary: A Python package to insert SVG images into PowerPoint presentations, with MCP server capabilities.
Author-email: NeekChaw <your.email@example.com>
Project-URL: Homepage, https://github.com/NeekChaw/mcp-server-okppt
Project-URL: Bug Tracker, https://github.com/NeekChaw/mcp-server-okppt/issues
Requires-Python: >=3.10
License-File: LICENSE
Requires-Dist: mcp[cli]>=1.8.0
Requires-Dist: lxml>=4.9.2
Requires-Dist: python-pptx>=0.6.21
Requires-Dist: reportlab>=4.0.0
Requires-Dist: svglib>=1.5.1
Requires-Dist: rlPyCairo>=0.1.0
Dynamic: license-file
